[{"nombre":"TallerDeJairo","sistema_asociado":"Hidraulico","interno_sede":"Ivan","reparar_en_ruta":true,"dinero_fallas_menores":100,"recolectores":[{"marca":"Audi","doble_troque":true,"id":112233,"disponible":true,"rutaid":123456,"ruta":{"id":123456,"horario":"6pm","dia":"Martes","recolector_id":112233,"estado_recolector":false},"talleres":[],"personas":[]},{"marca":"Caterpilar","doble_troque":false,"id":789,"disponible":true,"rutaid":4524,"ruta":{"id":4524,"horario":"8am","dia":"Viernes","recolector_id":789,"estado_recolector":true},"talleres":[],"personas":[]}],"personas":[]},{"nombre":"LosMecanicos","sistema_asociado":"Transmision","interno_sede":"Guillermo","reparar_en_ruta":false,"dinero_fallas_menores":500,"recolectores":[],"personas":[{"perfil":"Electricista","horario":"Diurno","cedula":70901147,"nombre":"Alberto","sueldo":800,"recolectores":[{"marca":"Toyota","doble_troque":true,"id":357,"disponible":false,"rutaid":2451,"ruta":{"id":2451,"horario":"1pm","dia":"Lunes","recolector_id":357,"estado_recolector":false},"talleres":[],"personas":[]}]}]},{"nombre":"Chatarreros","sistema_asociado":"Soldadura","interno_sede":"Pablo","reparar_en_ruta":true,"dinero_fallas_menores":1000,"recolectores":[{"marca":"Toyota","doble_troque":true,"id":357,"disponible":false,"rutaid":2451,"ruta":{"id":2451,"horario":"1pm","dia":"Lunes","recolector_id":357,"estado_recolector":false},"talleres":[],"personas":[]}],"personas":[{"perfil":"Ejecutivo","horario":"Nocturno","cedula":1007290916,"nombre":"Valentin","sueldo":500,"recolectores":[{"marca":"Audi","doble_troque":true,"id":112233,"disponible":true,"rutaid":123456,"ruta":{"id":123456,"horario":"6pm","dia":"Martes","recolector_id":112233,"estado_recolector":false},"talleres":[],"personas":[]}]}]}]